{
  "leaves": [
    {
      "leaveCode": "55886151331",
      "serviceCode": "55886151331",
      "nationalId": "1128193651",
      "idNumber": "1128193651",
      "name": "ياسر ماهر عبدالرحيم محمد رجب",
      "admissionDate": "2025-06-11",
      "dischargeDate": "2025-06-11",
      "leaveDuration": "1",
      "doctorName": "علي بكر",
      "jobTitle": "طب بشري",
      "issueDate": "2025-06-11",
      "leaveType": "اعتيادية"
    },
    {
      "leaveCode": "03644334841",
      "serviceCode": "03644334841",
      "nationalId": "1124402502",
      "idNumber": "1124402502",
      "name": "عبدالملك مخلد عقلاء الشمري  ",
      "admissionDate": "2026-01-27",
      "dischargeDate": "2026-01-27",
      "leaveDuration": "1",
      "doctorName": "أحمد سليمان الجباري",
      "jobTitle": "استشاري أمراض الباطنية",
      "issueDate": "2026-01-27",
      "leaveType": "GSL"
    },
    {
      "leaveCode": "PSL26070934213",
      "serviceCode": "PSL26070934213",
      "nationalId": "1234554555",
      "idNumber": "1234554555",
      "name": "علي حامد محمد الشمراني",
      "admissionDate": "2026-07-09",
      "dischargeDate": "2026-07-13",
      "leaveDuration": "5",
      "doctorName": "محمد زيان",
      "jobTitle": "أخصائي طب عام",
      "issueDate": "2026-07-13",
      "leaveType": "إجازة مرضية"
    },
    {
      "leaveCode": "PSL26071446121",
      "serviceCode": "PSL26071446121",
      "nationalId": "1070829070",
      "idNumber": "1070829070",
      "name": "عائشه جبران احمد المالكي",
      "admissionDate": "2026-07-14",
      "dischargeDate": "2026-07-14",
      "leaveDuration": "1",
      "doctorName": "سعيد محمد نجيب الحوت",
      "jobTitle": "طبيب عام ",
      "issueDate": "2026-07-14",
      "leaveType": "إجازة مرضية"
    },
    {
      "leaveCode": "GSL26071393017",
      "serviceCode": "GSL26071393017",
      "nationalId": "1129449003",
      "idNumber": "1129449003",
      "name": "احمد سعد حتيم الشمري",
      "admissionDate": "2026-07-09",
      "dischargeDate": "2026-07-13",
      "leaveDuration": "5",
      "doctorName": "هند محمد علي عثمان الشايف",
      "jobTitle": "نائب باطنية",
      "issueDate": "2026-07-13",
      "leaveType": "إجازة مرضية"
    },
    {
      "leaveCode": "PSL26071447438",
      "serviceCode": "PSL26071447438",
      "nationalId": "1070829070",
      "idNumber": "1070829070",
      "name": "عائشه جبران المالكي ",
      "admissionDate": "2026-07-11",
      "dischargeDate": "2026-07-11",
      "leaveDuration": "1",
      "doctorName": "سعيد محمد نجيب الحوت",
      "jobTitle": "طبيب عام",
      "issueDate": "2026-07-14",
      "leaveType": "إجازة مرضية"
    },
    {
      "leaveCode": "GSL26071198243",
      "serviceCode": "GSL26071198243",
      "nationalId": "1057892042",
      "idNumber": "1057892042",
      "name": "هنادي احمد محمد المغربي ",
      "admissionDate": "2026-07-12",
      "dischargeDate": "2026-07-12",
      "leaveDuration": "1",
      "doctorName": "مشعل الغامدي",
      "jobTitle": "طبيب عام",
      "issueDate": "2026-07-12",
      "leaveType": "إجازة مرضية"
    },
    {
      "leaveCode": "GSL26071298243",
      "serviceCode": "GSL26071298243",
      "nationalId": "1057892042",
      "idNumber": "1057892042",
      "name": "هنادي احمد محمد المغربي ",
      "admissionDate": "2026-07-12",
      "dischargeDate": "2026-07-12",
      "leaveDuration": "1",
      "doctorName": "مشعل الغامدي",
      "jobTitle": "طبيب عام",
      "issueDate": "2026-07-12",
      "leaveType": "إجازة مرضية"
    },
    {
      "leaveCode": "GSL26071297689",
      "serviceCode": "GSL26071297689",
      "nationalId": "1128741285 ",
      "idNumber": "1128741285 ",
      "name": "سارة سالم الصيعريي",
      "admissionDate": "2026-07-10",
      "dischargeDate": "2026-07-10",
      "leaveDuration": "1",
      "doctorName": "ياسر المحمدي",
      "jobTitle": "نائب أول باطنية",
      "issueDate": "2026-07-10",
      "leaveType": "إجازة مرضية"
    },
    {
      "leaveCode": "GSL26071213101",
      "serviceCode": "GSL26071213101",
      "nationalId": "1137282164",
      "idNumber": "1137282164",
      "name": "سعد مسند مقيم السبيعي ",
      "admissionDate": "2026-07-12",
      "dischargeDate": "2026-07-12",
      "leaveDuration": "1",
      "doctorName": "عاصم الشريف",
      "jobTitle": "استشاري باطنية",
      "issueDate": "2026-07-12",
      "leaveType": "إجازة مرضية"
    },
    {
      "leaveCode": "PSL26071325627",
      "serviceCode": "PSL26071325627",
      "nationalId": "1106870288",
      "idNumber": "1106870288",
      "name": "علي صالح علي الشمراني",
      "admissionDate": "2026-07-11",
      "dischargeDate": "2026-07-16",
      "leaveDuration": "6",
      "doctorName": "علي القحطاني",
      "jobTitle": "طبيب عام",
      "issueDate": "2026-07-13",
      "leaveType": "إجازة مرضية"
    },
    {
      "leaveCode": "GSL26071469050",
      "serviceCode": "GSL26071469050",
      "nationalId": "1136783451",
      "idNumber": "1136783451",
      "name": "غدير راضي صالح الرويلي ",
      "admissionDate": "2026-07-14",
      "dischargeDate": "2026-07-15",
      "leaveDuration": "2",
      "doctorName": "رانيا سليم",
      "jobTitle": " استشاري",
      "issueDate": "2026-07-14",
      "leaveType": "إجازة مرضية"
    },
    {
      "leaveCode": "GSL26071445720",
      "serviceCode": "GSL26071445720",
      "nationalId": "1134584315",
      "idNumber": "1134584315",
      "name": "راما هاني الحربي",
      "admissionDate": "2026-07-14",
      "dischargeDate": "2026-07-14",
      "leaveDuration": "1",
      "doctorName": "محمد الجزار",
      "jobTitle": "أخصائي الطب الباطني ",
      "issueDate": "2026-07-14",
      "leaveType": "إجازة مرضية"
    }
  ]
}